appengine_python_standard-1.1.10-py3.13-nspkg.pth
google/appengine/__init__.py
google/appengine/_internal/__init__.py
google/appengine/_internal/antlr3/__init__.py
google/appengine/_internal/antlr3/compat.py
google/appengine/_internal/antlr3/constants.py
google/appengine/_internal/antlr3/dfa.py
google/appengine/_internal/antlr3/dottreegen.py
google/appengine/_internal/antlr3/exceptions.py
google/appengine/_internal/antlr3/extras.py
google/appengine/_internal/antlr3/main.py
google/appengine/_internal/antlr3/recognizers.py
google/appengine/_internal/antlr3/streams.py
google/appengine/_internal/antlr3/tokens.py
google/appengine/_internal/antlr3/tree.py
google/appengine/_internal/antlr3/treewizard.py
google/appengine/_internal/protorpc/__init__.py
google/appengine/_internal/protorpc/definition.py
google/appengine/_internal/protorpc/descriptor.py
google/appengine/_internal/protorpc/descriptor2py.py
google/appengine/_internal/protorpc/gen_protorpc.py
google/appengine/_internal/protorpc/generate.py
google/appengine/_internal/protorpc/generate_proto.py
google/appengine/_internal/protorpc/generate_python.py
google/appengine/_internal/protorpc/message_types.py
google/appengine/_internal/protorpc/messages.py
google/appengine/_internal/protorpc/non_sdk_imports.py
google/appengine/_internal/protorpc/protobuf.py
google/appengine/_internal/protorpc/protobuf_base.py
google/appengine/_internal/protorpc/protojson.py
google/appengine/_internal/protorpc/protourlencode.py
google/appengine/_internal/protorpc/registry.py
google/appengine/_internal/protorpc/remote.py
google/appengine/_internal/protorpc/transport.py
google/appengine/_internal/protorpc/util.py
google/appengine/_internal/protorpc/wsgi/__init__.py
google/appengine/_internal/protorpc/wsgi/service.py
google/appengine/_internal/protorpc/wsgi/util.py
google/appengine/api/__init__.py
google/appengine/api/api_base_pb2.py
google/appengine/api/api_testutil.py
google/appengine/api/apiproxy_rpc.py
google/appengine/api/apiproxy_stub.py
appengine_python_standard-1.1.10.dist-info/LICENSE
appengine_python_standard-1.1.10.dist-info/METADATA
appengine_python_standard-1.1.10.dist-info/WHEEL
appengine_python_standard-1.1.10.dist-info/namespace_packages.txt
appengine_python_standard-1.1.10.dist-info/top_level.txt
appengine_python_standard-1.1.10.dist-info/RECORD
