Metadata-Version: 2.2
Name: appengine-python-standard
Version: 1.1.10
Summary: Google App Engine services SDK for Python 3
Home-page: https://github.com/GoogleCloudPlatform/appengine-python-standard
Author: Google LLC
Classifier: Programming Language :: Python :: 3
Classifier: License :: OSI Approved :: MIT License
Classifier: Operating System :: OS Independent
Requires-Python: >=3.6, <4
License-File: LICENSE
Requires-Dist: attrs>=21.2.0
Requires-Dist: frozendict>=1.2
Requires-Dist: google-auth>=1.31.0
Requires-Dist: mock>=4.0.3
Requires-Dist: Pillow>=8.3.1
Requires-Dist: protobuf>=3.19.0
Requires-Dist: pytz>=2021.1
Requires-Dist: requests>=2.25.1
Requires-Dist: ruamel.yaml>=0.17.7
Requires-Dist: six>=1.15.0
Requires-Dist: urllib3<2,>=1.26.2
Requires-Dist: legacy-cgi>=2.6.2; python_version >= "3.10"
Dynamic: author
Dynamic: classifier
Dynamic: description
Dynamic: description-content-type
Dynamic: home-page
Dynamic: requires-dist
Dynamic: requires-python
Dynamic: summary
